chapa/__init__.py
chapa/api.py
chapa/webhook.py
chapa-0.1.2.dist-info/LICENSE
chapa-0.1.2.dist-info/METADATA
chapa-0.1.2.dist-info/WHEEL
chapa-0.1.2.dist-info/top_level.txt
chapa-0.1.2.dist-info/RECORD
