Metadata-Version: 2.1
Name: chapa
Version: 0.1.2
Summary: Python SDK for Chapa API https://developer.chapa.co
Home-page: https://github.com/chapimenge3/chapa
Author: Temkin Mengistu (Chapi)
Author-email: chapimenge3@gmail.com
Project-URL: Source, https://github.com/chapimenge3/chapa
Project-URL: Bug Tracker, https://github.com/chapimenge3/chapa/issues
Classifier: Programming Language :: Python :: 3
Classifier: License :: OSI Approved :: MIT License
Classifier: Operating System :: OS Independent
Classifier: Development Status :: 3 - Alpha
Classifier: Intended Audience :: Developers
Classifier: Topic :: Software Development :: Libraries :: Python Modules
Requires-Python: >=3.6
License-File: LICENSE
Requires-Dist: httpx>=0.27.0
